fieldedge_pcap/__init__.py
fieldedge_pcap/constants.py
fieldedge_pcap/pyshark.py
fieldedge_pcap-0.3.0.dist-info/LICENSE
fieldedge_pcap-0.3.0.dist-info/WHEEL
fieldedge_pcap-0.3.0.dist-info/METADATA
fieldedge_pcap-0.3.0.dist-info/RECORD
