Metadata-Version: 2.1
Name: fieldedge-pcap
Version: 0.3.0
Summary: Library and models for working with packet capture and analysis.
License: Apache2.0
Author: geoffbrucepayne
Author-email: geoff.bruce-payne@inmarsat.com
Requires-Python: >=3.7,<4.0
Classifier: License :: Other/Proprietary License
Classifier: Programming Language :: Python :: 3
Classifier: Programming Language :: Python :: 3.10
Classifier: Programming Language :: Python :: 3.7
Classifier: Programming Language :: Python :: 3.8
Classifier: Programming Language :: Python :: 3.9
Requires-Dist: pyshark (>=0.5.3,<0.6.0)
